meshgpt_pytorch/__init__.py
meshgpt_pytorch/data.py
meshgpt_pytorch/meshgpt_pytorch.py
meshgpt_pytorch/trainer.py
meshgpt_pytorch/typing.py
meshgpt_pytorch/version.py
meshgpt_pytorch-1.8.1.dist-info/LICENSE
meshgpt_pytorch-1.8.1.dist-info/METADATA
meshgpt_pytorch-1.8.1.dist-info/WHEEL
meshgpt_pytorch-1.8.1.dist-info/top_level.txt
meshgpt_pytorch-1.8.1.dist-info/RECORD
