Metadata-Version: 2.1
Name: meshgpt-pytorch
Version: 1.8.1
Summary: MeshGPT Pytorch
Home-page: https://github.com/lucidrains/meshgpt-pytorch
Author: Phil Wang
Author-email: lucidrains@gmail.com
License: MIT
Keywords: artificial intelligence,deep learning,attention mechanisms,transformers,mesh generation
Classifier: Development Status :: 4 - Beta
Classifier: Intended Audience :: Developers
Classifier: Topic :: Scientific/Engineering :: Artificial Intelligence
Classifier: License :: OSI Approved :: MIT License
Classifier: Programming Language :: Python :: 3.6
License-File: LICENSE
Requires-Dist: accelerate>=0.25.0
Requires-Dist: beartype
Requires-Dist: huggingface_hub>=0.21.4
Requires-Dist: classifier-free-guidance-pytorch>=0.7.1
Requires-Dist: einops>=0.8.0
Requires-Dist: einx[torch]>=0.3.0
Requires-Dist: ema-pytorch>=0.5.1
Requires-Dist: environs
Requires-Dist: gateloop-transformer>=0.2.2
Requires-Dist: jaxtyping
Requires-Dist: local-attention>=1.9.11
Requires-Dist: numpy
Requires-Dist: pytorch-custom-utils>=0.0.9
Requires-Dist: rotary-embedding-torch>=0.6.4
Requires-Dist: sentencepiece
Requires-Dist: taylor-series-linear-attention==0.1.11
Requires-Dist: torch>=2.1
Requires-Dist: torch_geometric
Requires-Dist: tqdm
Requires-Dist: vector-quantize-pytorch>=1.18.1
Requires-Dist: x-transformers>=1.43.4
